pygrpy/__init__.py
pygrpy/grpy.py
pygrpy/grpy_tensors.py
pygrpy/jax_grpy_tensors.py
pygrpy/pdb_loader.py
PyGRPY-0.1.3.dist-info/LICENSE
PyGRPY-0.1.3.dist-info/METADATA
PyGRPY-0.1.3.dist-info/WHEEL
PyGRPY-0.1.3.dist-info/top_level.txt
PyGRPY-0.1.3.dist-info/RECORD
