Metadata-Version: 2.1
Name: PyGRPY
Version: 0.1.3
Summary: Python port of Generalized Rotne Prager Yakamava tensors
Home-page: https://github.com/RadostW/PyGRPY/
Author: Radost Waszkiewicz
Author-email: radost.waszkiewicz@gmail.com
License: GNU GPLv3
Project-URL: Documentation, https://pygrpy.readthedocs.io
Project-URL: Source, https://github.com/RadostW/PyGRPY/
Platform: UNKNOWN
License-File: LICENSE
